pulp_ostree/__init__.py
pulp_ostree/app/__init__.py
pulp_ostree/app/models.py
pulp_ostree/app/serializers.py
pulp_ostree/app/viewsets.py
pulp_ostree/app/migrations/0001_initial.py
pulp_ostree/app/migrations/0002_add_relative_path_uniqueness.py
pulp_ostree/app/migrations/0003_create_many_to_many_objs_commits.py
pulp_ostree/app/migrations/0004_add_include_exclude_refs.py
pulp_ostree/app/migrations/0005_add_static_delta_support.py
pulp_ostree/app/migrations/0006_alter_pointers_to_related_models_globally.py
pulp_ostree/app/migrations/0007_add_model_permissions.py
pulp_ostree/app/migrations/0008_add_domain_support.py
pulp_ostree/app/migrations/__init__.py
pulp_ostree/app/tasks/__init__.py
pulp_ostree/app/tasks/importing.py
pulp_ostree/app/tasks/modifying.py
pulp_ostree/app/tasks/stages.py
pulp_ostree/app/tasks/synchronizing.py
pulp_ostree/app/tasks/utils.py
pulp_ostree/tests/__init__.py
pulp_ostree/tests/functional/__init__.py
pulp_ostree/tests/functional/conftest.py
pulp_ostree/tests/functional/constants.py
pulp_ostree/tests/functional/utils.py
pulp_ostree/tests/functional/api/__init__.py
pulp_ostree/tests/functional/api/test_domain.py
pulp_ostree/tests/functional/api/test_filter.py
pulp_ostree/tests/functional/api/test_import.py
pulp_ostree/tests/functional/api/test_modify.py
pulp_ostree/tests/functional/api/test_rbac.py
pulp_ostree/tests/functional/api/test_sync.py
pulp_ostree/tests/performance/__init__.py
pulp_ostree/tests/unit/__init__.py
pulp_ostree/tests/unit/test_models.py
pulp_ostree/tests/upgrade/__init__.py
pulp_ostree/tests/upgrade/post/__init__.py
pulp_ostree/tests/upgrade/pre/__init__.py
pulp_ostree-2.6.0.dist-info/licenses/LICENSE
pulp_ostree-2.6.0.dist-info/METADATA
pulp_ostree-2.6.0.dist-info/WHEEL
pulp_ostree-2.6.0.dist-info/entry_points.txt
pulp_ostree-2.6.0.dist-info/top_level.txt
pulp_ostree-2.6.0.dist-info/RECORD
