Metadata-Version: 2.4
Name: pulp-ostree
Version: 2.6.0
Summary: OSTree plugin for the Pulp Project
Author-email: Pulp Project Developers <pulp-list@redhat.com>
Project-URL: Homepage, https://pulpproject.org
Project-URL: Documentation, https://pulpproject.org/pulp_ostree/
Project-URL: Repository, https://github.com/pulp/pulp_ostree
Project-URL: Bug Tracker, https://github.com/pulp/pulp_ostree/issues
Project-URL: Changelog, https://pulpproject.org/pulp_ostree/changes/
Classifier: License :: OSI Approved :: GNU General Public License v2 or later (GPLv2+)
Classifier: Operating System :: POSIX :: Linux
Classifier: Development Status :: 5 - Production/Stable
Classifier: Framework :: Django
Classifier: Programming Language :: Python
Classifier: Programming Language :: Python :: 3
Requires-Python: >=3.11
License-File: LICENSE
Requires-Dist: pulpcore<3.115,>=3.49.0
Requires-Dist: PyGObject<3.51,>=3.40.1
Dynamic: license-file
